LICENSE.txt
README.md
setup.cfg
setup.py
result4utility/__init__.py
result4utility/decorators.py
result4utility/dictionary.py
result4utility/encoder.py
result4utility/operations.py
result4utility/result.py
result4utility/tools.py
result4utility.egg-info/PKG-INFO
result4utility.egg-info/SOURCES.txt
result4utility.egg-info/dependency_links.txt
result4utility.egg-info/top_level.txt