Metadata-Version: 2.1
Name: result4utility
Version: 0.1.2
Summary: Result For Utility Tools
Home-page: https://github.com/luigi-dv/result4utility
Download-URL: https://github.com/luigi-dv/result4utility
Author: Luigelo Davila Vilchez
Author-email: luigelo@ldvloper.com
Keywords: Restful,Rest,Util,Tools
Classifier: Programming Language :: Python :: 3
Classifier: Programming Language :: Python :: 3.5
Classifier: Programming Language :: Python :: 3.6
Classifier: Programming Language :: Python :: 3.7
Classifier: Programming Language :: Python :: 3.8
Classifier: Programming Language :: Python :: 3.9
Classifier: Programming Language :: Python :: 3.10
Classifier: Programming Language :: Python :: 3.11
License-File: LICENSE.txt
